graphdj/__init__.py
graphdj/apps.py
graphdj/middleware.py
graphdj/models.py
graphdj/core/__base__.py
graphdj/core/__init__.py
graphdj/core/access.py
graphdj/core/base_model.py
graphdj/core/create_docs.py
graphdj/core/create_mutation.py
graphdj/core/create_node.py
graphdj/core/create_query.py
graphdj/core/get_fields.py
graphdj/core/pluralize.py
graphdj/management/__init__.py
graphdj/management/commands/__init__.py
graphdj/management/commands/build-models.py
graphdj/management/commands/build-roles.py
graphdj/management/commands/create-app.py
graphdj/management/templates/django_app_template.zip
graphdj-0.1.6.dist-info/LICENSE
graphdj-0.1.6.dist-info/METADATA
graphdj-0.1.6.dist-info/WHEEL
graphdj-0.1.6.dist-info/top_level.txt
graphdj-0.1.6.dist-info/RECORD
