Metadata-Version: 2.1
Name: graphdj
Version: 0.1.6
Summary: Easy CRUD with Graphene-Django
Home-page: https://github.com/hlop3z/graphdj
Author: hlop3z
Author-email: graphdj@googlegroups.com
License: UNKNOWN
Download-URL: https://github.com/hlop3z/graphdj/releases/download/v0.1.6-alpha/graphdj-0.1.6.tar.gz
Project-URL: Documentation, https://hlop3z.github.io/graphdj/
Keywords: module django crud graphql graphene-django
Platform: UNKNOWN
Classifier: License :: OSI Approved :: BSD License
Classifier: Intended Audience :: Developers
Classifier: Programming Language :: Python :: 3
Classifier: Programming Language :: Python :: 3.9
Classifier: Framework :: Django :: 3.2
Classifier: Development Status :: 3 - Alpha
Classifier: Topic :: Utilities
Requires-Python: >=3.9
License-File: LICENSE
Requires-Dist: Django (>=3.2)
Requires-Dist: graphene-django (>=3.0.0b7)
Requires-Dist: django-filter (>=2.4.0)
Requires-Dist: PyYAML (>=5.4.1)
Requires-Dist: python-json-logger (>=2.0.2)
